explore_package/__init__.py
explore_package-3.1.dist-info/METADATA
explore_package-3.1.dist-info/WHEEL
explore_package-3.1.dist-info/top_level.txt
explore_package-3.1.dist-info/RECORD
